<?xml version="1.0" encoding="utf-8"?>
<Strings>
    <Preferences>.\Preferences.json</Preferences>
    <WindowTitle>グロリアス</WindowTitle>
    <Docks>
        <Cpu>Cpu</Cpu>
    </Docks>
    <Menu>
        <FileMenu><![CDATA[&File]]></FileMenu>
        <File>
            <Open Tip="Open">Open</Open>
            <Attach>Attach</Attach>
            <Detach>Detach</Detach>
            <Exit>Exit</Exit>
        </File>

        <ViewMenu><![CDATA[&View]]></ViewMenu>
        <View>
            <Log><![CDATA[&Log]]></Log>
            <Modules><![CDATA[&Modules]]></Modules>
            <Memory><![CDATA[&Memory]]></Memory>
        </View>
    </Menu>
</Strings>
